odoo8_addon_mail_tracking_mailgun-8.0.1.0.0.99.dev10-py2.7-nspkg.pth
odoo8_addon_mail_tracking_mailgun-8.0.1.0.0.99.dev10.dist-info/DESCRIPTION.rst
odoo8_addon_mail_tracking_mailgun-8.0.1.0.0.99.dev10.dist-info/METADATA
odoo8_addon_mail_tracking_mailgun-8.0.1.0.0.99.dev10.dist-info/RECORD
odoo8_addon_mail_tracking_mailgun-8.0.1.0.0.99.dev10.dist-info/WHEEL
odoo8_addon_mail_tracking_mailgun-8.0.1.0.0.99.dev10.dist-info/metadata.json
odoo8_addon_mail_tracking_mailgun-8.0.1.0.0.99.dev10.dist-info/namespace_packages.txt
odoo8_addon_mail_tracking_mailgun-8.0.1.0.0.99.dev10.dist-info/top_level.txt
odoo_addons/mail_tracking_mailgun/README.rst
odoo_addons/mail_tracking_mailgun/__init__.py
odoo_addons/mail_tracking_mailgun/__openerp__.py
odoo_addons/mail_tracking_mailgun/i18n/ca.po
odoo_addons/mail_tracking_mailgun/i18n/de.po
odoo_addons/mail_tracking_mailgun/i18n/es.po
odoo_addons/mail_tracking_mailgun/i18n/fi.po
odoo_addons/mail_tracking_mailgun/i18n/fr.po
odoo_addons/mail_tracking_mailgun/i18n/mail_tracking_mailgun.pot
odoo_addons/mail_tracking_mailgun/i18n/sl.po
odoo_addons/mail_tracking_mailgun/models/__init__.py
odoo_addons/mail_tracking_mailgun/models/ir_mail_server.py
odoo_addons/mail_tracking_mailgun/models/mail_tracking_email.py
odoo_addons/mail_tracking_mailgun/static/description/icon.png
odoo_addons/mail_tracking_mailgun/static/description/icon.svg
odoo_addons/mail_tracking_mailgun/tests/__init__.py
odoo_addons/mail_tracking_mailgun/tests/test_mailgun.py
